n-bit CSA/MUX.v
// file: MUX.v
// author: @amrgouhar

`timescale 1ns/1ns

module MUX(A, B, Sel, Out);
parameter n =4;
input [n-1: 0] A, B;
input Sel;
output [n-1:0]Out;

assign {Out} = (Sel)? {A}:{B};
endmodule

4-bit CLA/CLA.v
// file: CLA.v
// author: @amrgouhar

`timescale 1ns/1ns

module CLA(A, B, Ci, Co, S, PG, GG);
input [3:0] A, B;
input Ci;
output Co;
output [3:0] S;
output PG, GG;
wire [3:0] P, G;
wire [4:0] C;
assign C[0] = Ci;
assign Co = C[4];
assign PG = P[0] & P[1] & P[2] & P[3];
assign GG = G[3] | (G[2] & P[3]) | (G[1] & P[3] & P[2]) | (G[0] & P[3] & P[2] & P[1]);

genvar i;
generate
    for(i = 0; i < 4; i = i + 1) begin
        assign  G[i] = A[i] & B[i];
        assign  P[i] = A[i] | B[i];
        assign  C[i + 1] = G[i] | (P[i] & C[i]); 
    end
endgenerate
generate
    for(i =0; i< 4; i = i + 1)
        assign S[i] = A[i] ^ B[i] ^ C[i];
endgenerate
endmodule

build (read-only)/RCA.netlist.v
/* Generated by Yosys 0.6 (git sha1 UNKNOWN, clang 3.4-1ubuntu3 -fPIC -Os) */

module FA(a, b, ci, co, s);
  wire _00_;
  wire _01_;
  wire _02_;
  wire _03_;
  wire _04_;
  wire _05_;
  wire _06_;
  input a;
  input b;
  input ci;
  output co;
  output s;
  AND2X2 _07_ (
    .A(a),
    .B(ci),
    .Y(_03_)
  );
  NOR2X1 _08_ (
    .A(a),
    .B(ci),
    .Y(_04_)
  );
  OAI21X1 _09_ (
    .A(_03_),
    .B(_04_),
    .C(b),
    .Y(_05_)
  );
  INVX1 _10_ (
    .A(b),
    .Y(_06_)
  );
  NAND2X1 _11_ (
    .A(a),
    .B(ci),
    .Y(_00_)
  );
  OR2X2 _12_ (
    .A(a),
    .B(ci),
    .Y(_01_)
  );
  NAND3X1 _13_ (
    .A(_06_),
    .B(_00_),
    .C(_01_),
    .Y(_02_)
  );
  NAND2X1 _14_ (
    .A(_05_),
    .B(_02_),
    .Y(s)
  );
  AOI21X1 _15_ (
    .A(_06_),
    .B(_00_),
    .C(_04_),
    .Y(co)
  );
endmodule

module RCA(A, B, Ci, Co, S);
  input [3:0] A;
  input [3:0] B;
  input Ci;
  output Co;
  output [3:0] S;
  wire [4:0] c;
  FA \addbit[0].bit  (
    .a(A[0]),
    .b(B[0]),
    .ci(Ci),
    .co(c[1]),
    .s(S[0])
  );
  FA \addbit[1].bit  (
    .a(A[1]),
    .b(B[1]),
    .ci(c[1]),
    .co(c[2]),
    .s(S[1])
  );
  FA \addbit[2].bit  (
    .a(A[2]),
    .b(B[2]),
    .ci(c[2]),
    .co(c[3]),
    .s(S[2])
  );
  FA \addbit[3].bit  (
    .a(A[3]),
    .b(B[3]),
    .ci(c[3]),
    .co(Co),
    .s(S[3])
  );
endmodule

n-bit CSA/CSA.v
// file: CSA.v
// author: @amrgouhar

`timescale 1ns/1ns

module CSA(A, B, Ci, Co, S);
parameter Type = 1;
parameter n = 16;
parameter k = 4;
input [n-1: 0] A, B;
input Ci;
output Co;
output [n-1:0] S;
wire [n/k:0] C;
wire [n-1:k] Stmp[1:0];
wire [1:0] Ctmp;
assign C[0] = Ci;
assign Co = C[n/k];

genvar i;
generate
    if(Type == 0 || k != 4) begin:addbit
        RCA #(k) bitN(.A(A[k-1:0]),.B(B[k-1:0]),.Ci(C[0]),.Co(C[1]), .S(S[k-1:0]));

    for(i =k; i < n; i = i +k)begin
        RCA #(k) bitA(.A(A[i+k-1:i]),.B(B[i+k-1:i]),.Ci(1'b0),.Co(Ctmp[0]), .S(Stmp[0][i+k-1:i]));
        RCA #(k) bitB(.A(A[i+k-1:i]),.B(B[i+k-1:i]),.Ci(1'b1),.Co(Ctmp[1]), .S(Stmp[1][i+k-1:i]));
        MUX #(k) bitX(.A(Stmp[1][i+k-1:i]),.B(Stmp[0][i+k-1:i]),.Sel(C[i/k]),.Out(S[i+k-1:i]));
        MUX #(1) bitZ(.A(Ctmp[1]),.B(Ctmp[0]),.Sel(C[i/k]),.Out(C[i/k + 1]));
    end
end
else begin:addbit
    CLA #(k) bitQ(.A(A[k-1:0]),.B(B[k-1:0]),.Ci(C[0]),.Co(C[1]), .S(S[k-1:0]));
    for(i =k; i < n; i = i +k)begin
        CLA #(k) bitW(.A(A[i+k-1:i]),.B(B[i+k-1:i]),.Ci(1'b0),.Co(Ctmp[0]), .S(Stmp[0][i+k-1:i]));
        CLA #(k) bitE(.A(A[i+k-1:i]),.B(B[i+k-1:i]),.Ci(1'b1),.Co(Ctmp[1]), .S(Stmp[1][i+k-1:i]));
        MUX #(k) bitR(.A(Stmp[1][i+k-1:i]),.B(Stmp[0][i+k-1:i]),.Sel(C[i/k]),.Out(S[i+k-1:i]));
        MUX #(1) bitT(.A(Ctmp[1]),.B(Ctmp[0]),.Sel(C[i/k]),.Out(C[i/k + 1]));
    end
    end
endgenerate
endmodule

n-bit CSA/CSA_tb.v
// file: CSA_tb.v
// author: @amrgouhar
// Testbench for CSA

`timescale 1ns/1ns

module CSA_tb;

	//Inputs
	reg [15: 0] A;
	reg [15: 0] B;
	reg Ci;


	//Outputs
	wire Co, ref_co, err;
	wire [15: 0] S, ref_s;


	//Instantiation of Unit Under Test
	CSA uut (
		.A(A),
		.B(B),
		.Ci(Ci),
		.Co(Co),
		.S(S)
	);
assign {ref_co, ref_s} = A+B+Ci;
assign err = (ref_s != S) || (ref_co != Co);

integer i, j, k;
	initial begin
	//Inputs initialization
		A = 0;
		B = 0;
		Ci = 0;
for(k=0; k<2; k = k+1) begin
    #5 Ci = k;
    for(i =0; i < 256; i= i+1)
        for(j=0; j < 16; j = j +1) begin
            #5 A = i;
            B= j;
        end
end
	//Wait for the reset
	

	end

endmodule

build (read-only)/CSA_tb.vcd
$date
	Sun Mar 19 16:41:16 2017
$end
$version
	Icarus Verilog
$end
$timescale
	1ns
$end
$scope module CSA_tb $end
$var wire 1 ! err $end
$var wire 16 " ref_s [15:0] $end
$var wire 1 # ref_co $end
$var wire 16 $ S [15:0] $end
$var wire 1 % Co $end
$var reg 16 & A [15:0] $end
$var reg 16 ' B [15:0] $end
$var reg 1 ( Ci $end
$var integer 32 ) i [31:0] $end
$var integer 32 * j [31:0] $end
$var integer 32 + k [31:0] $end
$scope module uut $end
$var wire 16 , A [15:0] $end
$var wire 16 - B [15:0] $end
$var wire 1 ( Ci $end
$var wire 2 . Ctmp [1:0] $end
$var wire 16 / S [15:0] $end
$var wire 1 % Co $end
$var wire 5 0 C [4:0] $end
$scope begin addbit $end
$scope begin genblk004 $end
$scope module bitE $end
$var wire 4 1 A [3:0] $end
$var wire 4 2 B [3:0] $end
$var wire 1 3 Ci $end
$var wire 1 4 GG $end
$var wire 1 5 PG $end
$var wire 4 6 S [3:0] $end
$var wire 4 7 P [3:0] $end
$var wire 4 8 G [3:0] $end
$var wire 1 9 Co $end
$var wire 5 : C [4:0] $end
$scope begin genblk0001 $end
$upscope $end
$scope begin genblk0002 $end
$upscope $end
$scope begin genblk001 $end
$upscope $end
$scope begin genblk002 $end
$upscope $end
$scope begin genblk01 $end
$upscope $end
$scope begin genblk02 $end
$upscope $end
$scope begin genblk1 $end
$upscope $end
$scope begin genblk2 $end
$upscope $end
$upscope $end
$scope module bitR $end
$var wire 4 ; A [3:0] $end
$var wire 4 < B [3:0] $end
$var wire 1 = Sel $end
$var wire 4 > Out [3:0] $end
$upscope $end
$scope module bitT $end
$var wire 1 ? A $end
$var wire 1 @ B $end
$var wire 1 A Sel $end
$var wire 1 B Out $end
$upscope $end
$scope module bitW $end
$var wire 4 C A [3:0] $end
$var wire 4 D B [3:0] $end
$var wire 1 E Ci $end
$var wire 1 F GG $end
$var wire 1 G PG $end
$var wire 4 H S [3:0] $end
$var wire 4 I P [3:0] $end
$var wire 4 J G [3:0] $end
$var wire 1 K Co $end
$var wire 5 L C [4:0] $end
$scope begin genblk0001 $end
$upscope $end
$scope begin genblk0002 $end
$upscope $end
$scope begin genblk001 $end
$upscope $end
$scope begin genblk002 $end
$upscope $end
$scope begin genblk01 $end
$upscope $end
$scope begin genblk02 $end
$upscope $end
$scope begin genblk1 $end
$upscope $end
$scope begin genblk2 $end
$upscope $end
$upscope $end
$upscope $end
$scope begin genblk04 $end
$scope module bitE $end
$var wire 4 M A [3:0] $end
$var wire 4 N B [3:0] $end
$var wire 1 O Ci $end
$var wire 1 P GG $end
$var wire 1 Q PG $end
$var wire 4 R S [3:0] $end
$var wire 4 S P [3:0] $end
$var wire 4 T G [3:0] $end
$var wire 1 U Co $end
$var wire 5 V C [4:0] $end
$scope begin genblk0001 $end
$upscope $end
$scope begin genblk0002 $end
$upscope $end
$scope begin genblk001 $end
$upscope $end
$scope begin genblk002 $end
$upscope $end
$scope begin genblk01 $end
$upscope $end
$scope begin genblk02 $end
$upscope $end
$scope begin genblk1 $end
$upscope $end
$scope begin genblk2 $end
$upscope $end
$upscope $end
$scope module bitR $end
$var wire 4 W A [3:0] $end
$var wire 4 X B [3:0] $end
$var wire 1 Y Sel $end
$var wire 4 Z Out [3:0] $end
$upscope $end
$scope module bitT $end
$var wire 1 [ A $end
$var wire 1 \ B $end
$var wire 1 ] Sel $end
$var wire 1 ^ Out $end
$upscope $end
$scope module bitW $end
$var wire 4 _ A [3:0] $end
$var wire 4 ` B [3:0] $end
$var wire 1 a Ci $end
$var wire 1 b GG $end
$var wire 1 c PG $end
$var wire 4 d S [3:0] $end
$var wire 4 e P [3:0] $end
$var wire 4 f G [3:0] $end
$var wire 1 g Co $end
$var wire 5 h C [4:0] $end
$scope begin genblk0001 $end
$upscope $end
$scope begin genblk0002 $end
$upscope $end
$scope begin genblk001 $end
$upscope $end
$scope begin genblk002 $end
$upscope $end
$scope begin genblk01 $end
$upscope $end
$scope begin genblk02 $end
$upscope $end
$scope begin genblk1 $end
$upscope $end
$scope begin genblk2 $end
$upscope $end
$upscope $end
$upscope $end
$scope begin genblk4 $end
$scope module bitE $end
$var wire 4 i A [3:0] $end
$var wire 4 j B [3:0] $end
$var wire 1 k Ci $end
$var wire 1 l GG $end
$var wire 1 m PG $end
$var wire 4 n S [3:0] $end
$var wire 4 o P [3:0] $end
$var wire 4 p G [3:0] $end
$var wire 1 q Co $end
$var wire 5 r C [4:0] $end
$scope begin genblk0001 $end
$upscope $end
$scope begin genblk0002 $end
$upscope $end
$scope begin genblk001 $end
$upscope $end
$scope begin genblk002 $end
$upscope $end
$scope begin genblk01 $end
$upscope $end
$scope begin genblk02 $end
$upscope $end
$scope begin genblk1 $end
$upscope $end
$scope begin genblk2 $end
$upscope $end
$upscope $end
$scope module bitR $end
$var wire 4 s A [3:0] $end
$var wire 4 t B [3:0] $end
$var wire 1 u Sel $end
$var wire 4 v Out [3:0] $end
$upscope $end
$scope module bitT $end
$var wire 1 w A $end
$var wire 1 x B $end
$var wire 1 y Sel $end
$var wire 1 z Out $end
$upscope $end
$scope module bitW $end
$var wire 4 { A [3:0] $end
$var wire 4 | B [3:0] $end
$var wire 1 } Ci $end
$var wire 1 ~ GG $end
$var wire 1 !" PG $end
$var wire 4 "" S [3:0] $end
$var wire 4 #" P [3:0] $end
$var wire 4 $" G [3:0] $end
$var wire 1 %" Co $end
$var wire 5 &" C [4:0] $end
$scope begin genblk0001 $end
$upscope $end
$scope begin genblk0002 $end
$upscope $end
$scope begin genblk001 $end
$upscope $end
$scope begin genblk002 $end
$upscope $end
$scope begin genblk01 $end
$upscope $end
$scope begin genblk02 $end
$upscope $end
$scope begin genblk1 $end
$upscope $end
$scope begin genblk2 $end
$upscope $end
$upscope $end
$upscope $end
$scope module bitQ $end
$var wire 4 '" A [3:0] $end
$var wire 4 (" B [3:0] $end
$var wire 1 )" Ci $end
$var wire 1 *" GG $end
$var wire 1 +" PG $end
$var wire 4 ," S [3:0] $end
$var wire 4 -" P [3:0] $end
$var wire 4 ." G [3:0] $end
$var wire 1 /" Co $end
$var wire 5 0" C [4:0] $end
$scope begin genblk0001 $end
$upscope $end
$scope begin genblk0002 $end
$upscope $end
$scope begin genblk001 $end
$upscope $end
$scope begin genblk002 $end
$upscope $end
$scope begin genblk01 $end
$upscope $end
$scope begin genblk02 $end
$upscope $end
$scope begin genblk1 $end
$upscope $end
$scope begin genblk2 $end
$upscope $end
$upscope $end
$upscope $end
$upscope $end
$upscope $end
$enddefinitions $end
#0
$dumpvars
b0 0"
0/"
b0 ."
b0 -"
b0 ,"
0+"
0*"
0)"
b0 ("
b0 '"
b0 &"
0%"
b0 $"
b0 #"
b0 ""
0!"
0~
0}
b0 |
b0 {
0z
0y
0x
0w
b0 v
0u
b0 t
b1 s
b1 r
0q
b0 p
b0 o
b1 n
0m
0l
1k
b0 j
b0 i
b0 h
0g
b0 f
b0 e
b0 d
0c
0b
0a
b0 `
b0 _
0^
0]
0\
0[
b0 Z
0Y
b0 X
b1 W
b1 V
0U
b0 T
b0 S
b1 R
0Q
0P
1O
b0 N
b0 M
b0 L
0K
b0 J
b0 I
b0 H
0G
0F
0E
b0 D
b0 C
0B
0A
0@
0?
b0 >
0=
b0 <
b1 ;
b1 :
09
b0 8
b0 7
b1 6
05
04
13
b0 2
b0 1
b0 0
b0 /
b0 .
b0 -
b0 ,
b0 +
bx *
bx )
0(
b0 '
b0 &
0%
b0 $
0#
b0 "
0!
$end
#5
b0 *
b0 )
#10
b1 *
#15
b1 $
b1 /
b1 ,"
b1 -"
0!
b1 "
b1 ("
b10 *
b1 '
b1 -
#20
b10 $
b10 /
b10 ,"
b10 -"
0!
b10 "
b10 ("
b11 *
b10 '
b10 -
#25
b11 $
b11 /
b11 ,"
b11 -"
0!
b11 "
b11 ("
b100 *
b11 '
b11 -
#30
b100 $
b100 /
b100 ,"
b100 -"
0!
b100 "
b100 ("
b101 *
b100 '
b100 -
#35
b101 $
b101 /
b101 ,"
b101 -"
0!
b101 "
b101 ("
b110 *
b101 '
b101 -
#40
b110 $
b110 /
b110 ,"
b110 -"
0!
b110 "
b110 ("
b111 *
b110 '
b110 -
#45
b111 $
b111 /
b111 ,"
b111 -"
0!
b111 "
b111 ("
b1000 *
b111 '
b111 -
#50
0+"
b1000 $
b1000 /
b1000 ,"
b1000 -"
0!
b1000 "
b1000 ("
b1001 *
b1000 '
b1000 -
#55
b1001 $
b1001 /
b1001 ,"
b1001 -"
0!
b1001 "
b1001 ("
b1010 *
b1001 '
b1001 -
#60
b1010 $
b1010 /
b1010 ,"
b1010 -"
0!
b1010 "
b1010 ("
b1011 *
b1010 '
b1010 -
#65
b1011 $
b1011 /
b1011 ,"
b1011 -"
0!
b1011 "
b1011 ("
b1100 *
b1011 '
b1011 -
#70
0+"
b1100 $
b1100 /
b1100 ,"
b1100 -"
0!
b1100 "
b1100 ("
b1101 *
b1100 '
b1100 -
#75
b1101 $
b1101 /
b1101 ,"
b1101 -"
0!
b1101 "
b1101 ("
b1110 *
b1101 '
b1101 -
#80
b1110 $
b1110 /
b1110 ,"
b1110 -"
0!
b1110 "
b1110 ("
b1111 *
b1110 '
b1110 -
#85
1+"
b1111 $
b1111 /
b1111 ,"
b1111 -"
0!
b1111 "
b1111 ("
b1 )
b0 *
b1111 '
b1111 -
#90
0+"
b1 $
b1 /
b1 ,"
b1 -"
0!
b0 ("
b1 "
b1 '"
b1 *
b0 '
b0 -
b1 &
b1 ,
#95
b10 0"
b10 $
b10 /
b10 ,"
b1 ."
0!
b10 "
b1 ("
b10 *
b1 '
b1 -
#100
b0 0"
b11 $
b11 /
b11 ,"
b0 ."
b11 -"
0!
b11 "
b10 ("
b11 *
b10 '
b10 -
#105
b110 0"
b100 $
b100 /
b100 ,"
b1 ."
0!
b100 "
b11 ("
b100 *
b11 '
b11 -
#110
b0 0"
b101 $
b101 /
b101 ,"
b0 ."
b101 -"
0!
b101 "
b100 ("
b101 *
b100 '
b100 -
#115
b10 0"
b110 $
b110 /
b110 ,"
b1 ."
0!
b110 "
b101 ("
b110 *
b101 '
b101 -
#120
b0 0"
b111 $
b111 /
b111 ,"
b0 ."
b111 -"
0!
b111 "
b110 ("
b111 *
b110 '
b110 -
#125
b1110 0"
b1000 $
b1000 /
b1000 ,"
b1 ."
0!
b1000 "
b111 ("
b1000 *
b111 '
b111 -
#130
b0 v
0y
0u
b0 0
0/"
b0 0"
0+"
b1001 $
b1001 /
b1001 ,"
b0 ."
b1001 -"
0!
b1001 "
b1000 ("
b1001 *
b1000 '
b1000 -
#135
b10 0"
b1010 $
b1010 /
b1010 ,"
b1 ."
0!
b1010 "
b1001 ("
b1010 *
b1001 '
b1001 -
#140
b0 0"
b1011 $
b1011 /
b1011 ,"
b0 ."
b1011 -"
0!
b1011 "
b1010 ("
b1011 *
b1010 '
b1010 -
#145
b110 0"
b1100 $
b1100 /
b1100 ,"
b1 ."
0!
b1100 "
b1011 ("
b1100 *
b1011 '
b1011 -
#150
b0 v
0y
0u
b0 0
0/"
0+"
b0 0"
b1101 $
b1101 /
b1101 ,"
b0 ."
b1101 -"
0!
b1101 "
b1100 ("
b1101 *
b1100 '
b1100 -
#155
b10 0"
b1110 $
b1110 /
b1110 ,"
b1 ."
0!
b1110 "
b1101 ("
b1110 *
b1101 '
b1101 -
#160
b0 v
0y
0u
b0 0
0/"
1+"
0*"
b0 0"
b1111 $
b1111 /
b1111 ,"
b0 ."
b1111 -"
0!
b1111 "
b1110 ("
b1111 *
b1110 '
b1110 -
#165
b1 v
1y
1u
b10 0
1/"
1*"
b11110 0"
b10000 $
b10000 /
b0 ,"
b1 ."
0!
b10000 "
b1111 ("
b10 )
b0 *
b1111 '
b1111 -
#170
b0 v
0y
0u
0*"
b0 0
0/"
0+"
b0 0"
b10 $
b10 /
b10 ,"
b0 ."
b10 -"
0!
b0 ("
b10 "
b10 '"
b1 *
b0 '
b0 -
b10 &
b10 ,
#175
b11 $
b11 /
b11 ,"
b11 -"
0!
b11 "
b1 ("
b10 *
b1 '
b1 -
#180
b100 0"
b100 $
b100 /
b100 ,"
b10 -"
b10 ."
0!
b100 "
b10 ("
b11 *
b10 '
b10 -
#185
b101 $
b101 /
b101 ,"
b11 -"
0!
b101 "
b11 ("
b100 *
b11 '
b11 -
#190
b0 0"
b110 $
b110 /
b110 ,"
b0 ."
b110 -"
0!
b110 "
b100 ("
b101 *
b100 '
b100 -
#195
b111 $
b111 /
b111 ,"
b111 -"
0!
b111 "
b101 ("
b110 *
b101 '
b101 -
#200
b1100 0"
b1000 $
b1000 /
b1000 ,"
b110 -"
b10 ."
0!
b1000 "
b110 ("
b111 *
b110 '
b110 -
#205
b1001 $
b1001 /
b1001 ,"
b111 -"
0!
b1001 "
b111 ("
b1000 *
b111 '
b111 -
#210
b0 v
0y
0u
b0 0
0/"
b0 0"
0+"
b1010 $
b1010 /
b1010 ,"
b0 ."
b1010 -"
0!
b1010 "
b1000 ("
b1001 *
b1000 '
b1000 -
#215
b1011 $
b1011 /
b1011 ,"
b1011 -"
0!
b1011 "
b1001 ("
b1010 *
b1001 '
b1001 -
#220
b100 0"
b1100 $
b1100 /
b1100 ,"
b1010 -"
b10 ."
0!
b1100 "
b1010 ("
b1011 *
b1010 '
b1010 -
#225
b1101 $
b1101 /
b1101 ,"
b1011 -"
0!
b1101 "
b1011 ("
b1100 *
b1011 '
b1011 -
#230
b0 v
0y
0u
b0 0
0/"
0*"
0+"
b0 0"
b1110 $
b1110 /
b1110 ,"
b0 ."
b1110 -"
0!
b1110 "
b1100 ("
b1101 *
b1100 '
b1100 -
#235
1+"
b1111 $
b1111 /
b1111 ,"
b1111 -"
0!
b1111 "
b1101 ("
b1110 *
b1101 '
b1101 -
#240
b1 v
1y
1u
b10 0
1/"
1*"
0+"
b11100 0"
b10000 $
b10000 /
b0 ,"
b1110 -"
b10 ."
0!
b10000 "
b1110 ("
b1111 *
b1110 '
b1110 -
#245
1+"
b10001 $
b10001 /
b1 ,"
b1111 -"
0!
b10001 "
b1111 ("
b11 )
b0 *
b1111 '
b1111 -
#250
b0 v
0y
0u
0*"
b0 0
0/"
b0 0"
0+"
b11 $
b11 /
b11 ,"
b0 ."
b11 -"
0!
b0 ("
b11 "
b11 '"
b1 *
b0 '
b0 -
b11 &
b11 ,
#255
b110 0"
b100 $
b100 /
b100 ,"
b1 ."
0!
b100 "
b1 ("
b10 *
b1 '
b1 -
#260
b100 0"
b101 $
b101 /
b101 ,"
b10 ."
0!
b101 "
b10 ("
b11 *
b10 '
b10 -
#265
b110 0"
b110 $
b110 /
b110 ,"
b11 ."
0!
b110 "
b11 ("
b100 *
b11 '
b11 -
#270
b0 0"
b111 $
b111 /
b111 ,"
b0 ."
b111 -"
0!
b111 "
b100 ("
b101 *
b100 '
b100 -
#275
b1110 0"
b1000 $
b1000 /
b1000 ,"
b1 ."
0!
b1000 "
b101 ("
b110 *
b101 '
b101 -
#280
b1100 0"
b1001 $
b1001 /
b1001 ,"
b10 ."
0!
b1001 "
b110 ("
b111 *
b110 '
b110 -
#285
b1110 0"
b1010 $
b1010 /
b1010 ,"
b11 ."
0!
b1010 "
b111 ("
b1000 *
b111 '
b111 -
#290
b0 v
0y
0u
b0 0
0/"
b0 0"
0+"
b1011 $
b1011 /
b1011 ,"
b0 ."
b1011 -"
0!
b1011 "
b1000 ("
b1001 *
b1000 '
b1000 -
#295
b110 0"
b1100 $
b1100 /
b1100 ,"
b1 ."
0!
b1100 "
b1001 ("
b1010 *
b1001 '
b1001 -
#300
b100 0"
b1101 $
b1101 /
b1101 ,"
b10 ."
0!
b1101 "
b1010 ("
b1011 *
b1010 '
b1010 -
#305
b110 0"
b1110 $
b1110 /
b1110 ,"
b11 ."
0!
b1110 "
b1011 ("
b1100 *
b1011 '
b1011 -
#310
b0 v
0y
0u
b0 0
0/"
0*"
1+"
b0 0"
b1111 $
b1111 /
b1111 ,"
b0 ."
b1111 -"
0!
b1111 "
b1100 ("
b1101 *
b1100 '
b1100 -
#315
b1 v
1y
1u
b10 0
1/"
1*"
b11110 0"
b10000 $
b10000 /
b0 ,"
b1 ."
0!
b10000 "
b1101 ("
b1110 *
b1101 '
b1101 -
#320
b11100 0"
b10001 $
b10001 /
b1 ,"
b10 ."
0!
b10001 "
b1110 ("
b1111 *
b1110 '
b1110 -
#325
b11110 0"
b10010 $
b10010 /
b10 ,"
b11 ."
0!
b10010 "
b1111 ("
b100 )
b0 *
b1111 '
b1111 -
#330
b0 v
0y
0u
0*"
b0 0
0/"
0+"
b0 0"
b100 $
b100 /
b100 ,"
b0 ."
b100 -"
0!
b0 ("
b100 "
b100 '"
b1 *
b0 '
b0 -
b100 &
b100 ,
#335
b101 $
b101 /
b101 ,"
b101 -"
0!
b101 "
b1 ("
b10 *
b1 '
b1 -
#340
b110 $
b110 /
b110 ,"
b110 -"
0!
b110 "
b10 ("
b11 *
b10 '
b10 -
#345
b111 $
b111 /
b111 ,"
b111 -"
0!
b111 "
b11 ("
b100 *
b11 '
b11 -
#350
b1000 0"
b1000 $
b1000 /
b1000 ,"
b100 -"
b100 ."
0!
b1000 "
b100 ("
b101 *
b100 '
b100 -
#355
b1001 $
b1001 /
b1001 ,"
b101 -"
0!
b1001 "
b101 ("
b110 *
b101 '
b101 -
#360
b1010 $
b1010 /
b1010 ,"
b110 -"
0!
b1010 "
b110 ("
b111 *
b110 '
b110 -
#365
b1011 $
b1011 /
b1011 ,"
b111 -"
0!
b1011 "
b111 ("
b1000 *
b111 '
b111 -
#370
b0 v
0y
0u
b0 0
0/"
b0 0"
0+"
b1100 $
b1100 /
b1100 ,"
b0 ."
b1100 -"
0!
b1100 "
b1000 ("
b1001 *
b1000 '
b1000 -
#375
b1101 $
b1101 /
b1101 ,"
b1101 -"
0!
b1101 "
b1001 ("
b1010 *
b1001 '
b1001 -
#380
b1110 $
b1110 /
b1110 ,"
b1110 -"
0!
b1110 "
b1010 ("
b1011 *
b1010 '
b1010 -
#385
1+"
b1111 $
b1111 /
b1111 ,"
b1111 -"
0!
b1111 "
b1011 ("
b1100 *
b1011 '
b1011 -
#390
b1 v
1y
1u
b10 0
1/"
1*"
0+"
b11000 0"
b10000 $
b10000 /
b0 ,"
b1100 -"
b100 ."
0!
b10000 "
b1100 ("
b1101 *
b1100 '
b1100 -
#395
b10001 $
b10001 /
b1 ,"
b1101 -"
0!
b10001 "
b1101 ("
b1110 *
b1101 '
b1101 -
#400
b10010 $
b10010 /
b10 ,"
b1110 -"
0!
b10010 "
b1110 ("
b1111 *
b1110 '
b1110 -
#405
1+"
b10011 $
b10011 /
b11 ,"
b1111 -"
0!
b10011 "
b1111 ("
b101 )
b0 *
b1111 '
b1111 -
#410
b0 v
0y
0u
0*"
b0 0
0/"
b0 0"
0+"
b101 $
b101 /
b101 ,"
b0 ."
b101 -"
0!
b0 ("
b101 "
b101 '"
b1 *
b0 '
b0 -
b101 &
b101 ,
#415
b10 0"
b110 $
b110 /
b110 ,"
b1 ."
0!
b110 "
b1 ("
b10 *
b1 '
b1 -
#420
b0 0"
b111 $
b111 /
b111 ,"
b0 ."
b111 -"
0!
b111 "
b10 ("
b11 *
b10 '
b10 -
#425
b1110 0"
b1000 $
b1000 /
b1000 ,"
b1 ."
0!
b1000 "
b11 ("
b100 *
b11 '
b11 -
#430
b1000 0"
b1001 $
b1001 /
b1001 ,"
b101 -"
b100 ."
0!
b1001 "
b100 ("
b101 *
b100 '
b100 -
#435
b1010 0"
b1010 $
b1010 /
b1010 ,"
b101 ."
0!
b1010 "
b101 ("
b110 *
b101 '
b101 -
#440
b1000 0"
b1011 $
b1011 /
b1011 ,"
b100 ."
b111 -"
0!
b1011 "
b110 ("
b111 *
b110 '
b110 -
#445
b1110 0"
b1100 $
b1100 /
b1100 ,"
b101 ."
0!
b1100 "
b111 ("
b1000 *
b111 '
b111 -
#450
b0 v
0y
0u
b0 0
0/"
b0 0"
0+"
b1101 $
b1101 /
b1101 ,"
b0 ."
b1101 -"
0!
b1101 "
b1000 ("
b1001 *
b1000 '
b1000 -
#455
b10 0"
b1110 $
b1110 /
b1110 ,"
b1 ."
0!
b1110 "
b1001 ("
b1010 *
b1001 '
b1001 -
#460
b0 v
0y
0u
b0 0
0/"
1+"
0*"
b0 0"
b1111 $
b1111 /
b1111 ,"
b0 ."
b1111 -"
0!
b1111 "
b1010 ("
b1011 *
b1010 '
b1010 -
#465
b1 v
1y
1u
b10 0
1/"
1*"
b11110 0"
b10000 $
b10000 /
b0 ,"
b1 ."
0!
b10000 "
b1011 ("
b1100 *
b1011 '
b1011 -
#470
0+"
1*"
b11000 0"
b10001 $
b10001 /
b1 ,"
b1101 -"
b100 ."
0!
b10001 "
b1100 ("
b1101 *
b1100 '
b1100 -
#475
b11010 0"
b10010 $
b10010 /
b10 ,"
b101 ."
0!
b10010 "
b1101 ("
b1110 *
b1101 '
b1101 -
#480
1+"
b11000 0"
b10011 $
b10011 /
b11 ,"
b100 ."
b1111 -"
0!
b10011 "
b1110 ("
b1111 *
b1110 '
b1110 -
#485
b11110 0"
b10100 $
b10100 /
b100 ,"
b101 ."
0!
b10100 "
b1111 ("
b110 )
b0 *
b1111 '
b1111 -
#490
b0 v
0y
0u
0*"
b0 0
0/"
0+"
b0 0"
b110 $
b110 /
b110 ,"
b0 ."
b110 -"
0!
b0 ("
b110 "
b110 '"
b1 *
b0 '
b0 -
b110 &
b110 ,
#495
b111 $
b111 /
b111 ,"
b111 -"
0!
b111 "
b1 ("
b10 *
b1 '
b1 -
#500
b1100 0"
b1000 $
b1000 /
b1000 ,"
b110 -"
b10 ."
0!
b1000 "
b10 ("
b11 *
b10 '
b10 -
#505
b1001 $
b1001 /
b1001 ,"
b111 -"
0!
b1001 "
b11 ("
b100 *
b11 '
b11 -
#510
b1000 0"
b1010 $
b1010 /
b1010 ,"
b110 -"
b100 ."
0!
b1010 "
b100 ("
b101 *
b100 '
b100 -
#515
b1011 $
b1011 /
b1011 ,"
b111 -"
0!
b1011 "
b101 ("
b110 *
b101 '
b101 -
#520
b1100 0"
b1100 $
b1100 /
b1100 ,"
b110 -"
b110 ."
0!
b1100 "
b110 ("
b111 *
b110 '
b110 -
#525
b1101 $
b1101 /
b1101 ,"
b111 -"
0!
b1101 "
b111 ("
b1000 *
b111 '
b111 -
#530
b0 v
0y
0u
b0 0
0/"
b0 0"
0+"
b1110 $
b1110 /
b1110 ,"
b0 ."
b1110 -"
0!
b1110 "
b1000 ("
b1001 *
b1000 '
b1000 -
#535
1+"
b1111 $
b1111 /
b1111 ,"
b1111 -"
0!
b1111 "
b1001 ("
b1010 *
b1001 '
b1001 -
#540
b1 v
1y
1u
b10 0
1/"
1*"
0+"
b11100 0"
b10000 $
b10000 /
b0 ,"
b1110 -"
b10 ."
0!
b10000 "
b1010 ("
b1011 *
b1010 '
b1010 -
#545
1+"
b10001 $
b10001 /
b1 ,"
b1111 -"
0!
b10001 "
b1011 ("
b1100 *
b1011 '
b1011 -
#550
0+"
b11000 0"
b10010 $
b10010 /
b10 ,"
b1110 -"
b100 ."
0!
b10010 "
b1100 ("
b1101 *
b1100 '
b1100 -
#555
1+"
b10011 $
b10011 /
b11 ,"
b1111 -"
0!
b10011 "
b1101 ("
b1110 *
b1101 '
b1101 -
#560
0+"
b11100 0"
b10100 $
b10100 /
b100 ,"
b1110 -"
b110 ."
0!
b10100 "
b1110 ("
b1111 *
b1110 '
b1110 -
#565
1+"
b10101 $
b10101 /
b101 ,"
b1111 -"
0!
b10101 "
b1111 ("
b111 )
b0 *
b1111 '
b1111 -
#570
b0 v
0y
0u
0*"
b0 0
0/"
b0 0"
0+"
b111 $
b111 /
b111 ,"
b0 ."
b111 -"
0!
b0 ("
b111 "
b111 '"
b1 *
b0 '
b0 -
b111 &
b111 ,
