build (read-only)/RCA.netlist.v
/* Generated by Yosys 0.6 (git sha1 UNKNOWN, clang 3.4-1ubuntu3 -fPIC -Os) */

module FA(a, b, ci, co, s);
  wire _00_;
  wire _01_;
  wire _02_;
  wire _03_;
  wire _04_;
  wire _05_;
  wire _06_;
  input a;
  input b;
  input ci;
  output co;
  output s;
  AND2X2 _07_ (
    .A(a),
    .B(ci),
    .Y(_03_)
  );
  NOR2X1 _08_ (
    .A(a),
    .B(ci),
    .Y(_04_)
  );
  OAI21X1 _09_ (
    .A(_03_),
    .B(_04_),
    .C(b),
    .Y(_05_)
  );
  INVX1 _10_ (
    .A(b),
    .Y(_06_)
  );
  NAND2X1 _11_ (
    .A(a),
    .B(ci),
    .Y(_00_)
  );
  OR2X2 _12_ (
    .A(a),
    .B(ci),
    .Y(_01_)
  );
  NAND3X1 _13_ (
    .A(_06_),
    .B(_00_),
    .C(_01_),
    .Y(_02_)
  );
  NAND2X1 _14_ (
    .A(_05_),
    .B(_02_),
    .Y(s)
  );
  AOI21X1 _15_ (
    .A(_06_),
    .B(_00_),
    .C(_04_),
    .Y(co)
  );
endmodule

module RCA(A, B, Ci, Co, S);
  input [3:0] A;
  input [3:0] B;
  input Ci;
  output Co;
  output [3:0] S;
  wire [4:0] c;
  FA \addbit[0].bit  (
    .a(A[0]),
    .b(B[0]),
    .ci(Ci),
    .co(c[1]),
    .s(S[0])
  );
  FA \addbit[1].bit  (
    .a(A[1]),
    .b(B[1]),
    .ci(c[1]),
    .co(c[2]),
    .s(S[1])
  );
  FA \addbit[2].bit  (
    .a(A[2]),
    .b(B[2]),
    .ci(c[2]),
    .co(c[3]),
    .s(S[2])
  );
  FA \addbit[3].bit  (
    .a(A[3]),
    .b(B[3]),
    .ci(c[3]),
    .co(Co),
    .s(S[3])
  );
endmodule

n-bit RCA/RCA_tb.v
// file: RCA_tb.v
// author: @amrgouhar
// Testbench for RCA

`timescale 1ns/1ns

module RCA_tb;

	//Inputs
	reg [3: 0] A;
	reg [3: 0] B;
	reg Ci;


	//Outputs
	wire Co, err, ref_co;
	wire [3: 0] S, ref_S;

	//Instantiation of Unit Under Test
	RCA uut (
		.A(A),
		.B(B),
		.Ci(Ci),
		.Co(Co),
		.S(S)
	);
    assign {ref_co, ref_S} = A + B + Ci;
    assign err = (ref_S != S) || (ref_co != Co);

integer i, j, k;
	initial begin
	//Inputs initialization
		A = 0;
		B = 0;
		Ci = 0;
for(k = 0; k < 2; k = k+1) begin
    #5 Ci = k;
    for(i = 0; i < 16; i= i+1)
        for(j =0; j < 16; j = j+1) begin
            #5  A = i;
            B = j;
        end
end
	//Wait for the reset
		#100;

	end

endmodule

build (read-only)/RCA_tb.vcd
$date
	Sun Mar 19 15:12:00 2017
$end
$version
	Icarus Verilog
$end
$timescale
	1ns
$end
$scope module RCA_tb $end
$var wire 1 ! err $end
$var wire 1 " ref_co $end
$var wire 4 # ref_S [3:0] $end
$var wire 4 $ S [3:0] $end
$var wire 1 % Co $end
$var reg 4 & A [3:0] $end
$var reg 4 ' B [3:0] $end
$var reg 1 ( Ci $end
$var integer 32 ) i [31:0] $end
$var integer 32 * j [31:0] $end
$var integer 32 + k [31:0] $end
$scope module uut $end
$var wire 4 , A [3:0] $end
$var wire 4 - B [3:0] $end
$var wire 1 ( Ci $end
$var wire 5 . c [4:0] $end
$var wire 4 / S [3:0] $end
$var wire 1 % Co $end
$scope begin addbit[0] $end
$scope module bit $end
$var wire 1 0 a $end
$var wire 1 1 b $end
$var wire 1 2 ci $end
$var wire 1 3 co $end
$var wire 1 4 s $end
$upscope $end
$upscope $end
$scope begin addbit[1] $end
$scope module bit $end
$var wire 1 5 a $end
$var wire 1 6 b $end
$var wire 1 7 ci $end
$var wire 1 8 co $end
$var wire 1 9 s $end
$upscope $end
$upscope $end
$scope begin addbit[2] $end
$scope module bit $end
$var wire 1 : a $end
$var wire 1 ; b $end
$var wire 1 < ci $end
$var wire 1 = co $end
$var wire 1 > s $end
$upscope $end
$upscope $end
$scope begin addbit[3] $end
$scope module bit $end
$var wire 1 ? a $end
$var wire 1 @ b $end
$var wire 1 A ci $end
$var wire 1 B co $end
$var wire 1 C s $end
$upscope $end
$upscope $end
$upscope $end
$upscope $end
$enddefinitions $end
#0
$dumpvars
0C
0B
0A
0@
0?
0>
0=
0<
0;
0:
09
08
07
06
05
04
03
02
01
00
b0 /
b0 .
b0 -
b0 ,
b0 +
bx *
bx )
0(
b0 '
b0 &
0%
b0 $
b0 #
0"
0!
$end
#5
b0 *
b0 )
#10
b1 *
#15
b1 $
b1 /
14
0!
b1 #
11
b10 *
b1 '
b1 -
#20
04
b10 $
b10 /
19
0!
b10 #
01
16
b11 *
b10 '
b10 -
#25
b11 $
b11 /
14
0!
b11 #
11
b100 *
b11 '
b11 -
#30
04
09
b100 $
b100 /
1>
0!
b100 #
01
06
1;
b101 *
b100 '
b100 -
#35
b101 $
b101 /
14
0!
b101 #
11
b110 *
b101 '
b101 -
#40
04
b110 $
b110 /
19
0!
b110 #
01
16
b111 *
b110 '
b110 -
#45
b111 $
b111 /
14
0!
b111 #
11
b1000 *
b111 '
b111 -
#50
04
09
0>
b1000 $
b1000 /
1C
0!
b1000 #
01
06
0;
1@
b1001 *
b1000 '
b1000 -
#55
b1001 $
b1001 /
14
0!
b1001 #
11
b1010 *
b1001 '
b1001 -
#60
04
b1010 $
b1010 /
19
0!
b1010 #
01
16
b1011 *
b1010 '
b1010 -
#65
b1011 $
b1011 /
14
0!
b1011 #
11
b1100 *
b1011 '
b1011 -
#70
04
09
b1100 $
b1100 /
1>
0!
b1100 #
01
06
1;
b1101 *
b1100 '
b1100 -
#75
b1101 $
b1101 /
14
0!
b1101 #
11
b1110 *
b1101 '
b1101 -
#80
04
b1110 $
b1110 /
19
0!
b1110 #
01
16
b1111 *
b1110 '
b1110 -
#85
b1111 $
b1111 /
14
0!
b1111 #
11
b1 )
b0 *
b1111 '
b1111 -
#90
09
0>
b1 $
b1 /
0C
0!
01
06
0;
0@
b1 #
10
b1 *
b0 '
b0 -
b1 &
b1 ,
#95
19
17
b10 .
13
b10 $
b10 /
04
0!
b10 #
11
b10 *
b1 '
b1 -
#100
07
0>
03
0<
14
b11 $
b11 /
19
b0 .
08
0!
b11 #
01
16
b11 *
b10 '
b10 -
#105
1>
1<
18
09
17
b110 .
13
b100 $
b100 /
04
0!
b100 #
11
b100 *
b11 '
b11 -
#110
07
0C
03
0<
0A
14
09
08
b101 $
b101 /
1>
b0 .
0=
0!
b101 #
01
06
1;
b101 *
b100 '
b100 -
#115
19
17
b10 .
13
b110 $
b110 /
04
0!
b110 #
11
b110 *
b101 '
b101 -
#120
0C
0A
0=
07
1>
03
0<
14
b111 $
b111 /
19
b0 .
08
0!
b111 #
01
16
b111 *
b110 '
b110 -
#125
1C
1A
1=
0>
1<
18
09
17
b1110 .
13
b1000 $
b1000 /
04
0!
b1000 #
11
b1000 *
b111 '
b111 -
#130
07
03
0<
0A
0%
14
09
08
0>
0=
b1001 $
b1001 /
1C
b0 .
0B
0!
b1001 #
01
06
0;
1@
b1001 *
b1000 '
b1000 -
#135
19
17
b10 .
13
b1010 $
b1010 /
04
0!
b1010 #
11
b1010 *
b1001 '
b1001 -
#140
07
0>
03
0<
14
b1011 $
b1011 /
19
b0 .
08
0!
b1011 #
01
16
b1011 *
b1010 '
b1010 -
#145
1>
1<
18
09
17
b110 .
13
b1100 $
b1100 /
04
0!
b1100 #
11
b1100 *
b1011 '
b1011 -
#150
0%
0B
07
1C
03
0<
0A
14
09
08
b1101 $
b1101 /
1>
b0 .
0=
0!
b1101 #
01
06
1;
b1101 *
b1100 '
b1100 -
#155
19
17
b10 .
13
b1110 $
b1110 /
04
0!
b1110 #
11
b1110 *
b1101 '
b1101 -
#160
0%
0B
1C
0A
0=
07
1>
03
0<
14
b1111 $
b1111 /
19
b0 .
08
0!
b1111 #
01
16
b1111 *
b1110 '
b1110 -
#165
1%
1B
0C
1A
1=
0>
1<
18
09
17
b11110 .
13
b0 $
b0 /
04
0!
b0 #
1"
11
b10 )
b0 *
b1111 '
b1111 -
#170
0<
08
19
07
0A
0%
03
0>
0=
b10 $
b10 /
0C
b0 .
0B
0!
0"
01
06
0;
0@
b10 #
00
15
b1 *
b0 '
b0 -
b10 &
b10 ,
#175
b11 $
b11 /
14
0!
b11 #
11
b10 *
b1 '
b1 -
#180
1>
1<
b100 .
18
04
b100 $
b100 /
09
0!
b100 #
01
16
b11 *
b10 '
b10 -
#185
b101 $
b101 /
14
0!
b101 #
11
b100 *
b11 '
b11 -
#190
0<
0C
08
0A
04
19
b110 $
b110 /
1>
b0 .
0=
0!
b110 #
01
06
1;
b101 *
b100 '
b100 -
#195
b111 $
b111 /
14
0!
b111 #
11
b110 *
b101 '
b101 -
#200
1C
1A
1=
0>
1<
b1100 .
18
04
b1000 $
b1000 /
09
0!
b1000 #
01
16
b111 *
b110 '
b110 -
#205
b1001 $
b1001 /
14
0!
b1001 #
11
b1000 *
b111 '
b111 -
#210
0<
08
0A
0%
04
19
0>
0=
b1010 $
b1010 /
1C
b0 .
0B
0!
b1010 #
01
06
0;
1@
b1001 *
b1000 '
b1000 -
#215
b1011 $
b1011 /
14
0!
b1011 #
11
b1010 *
b1001 '
b1001 -
#220
1>
1<
b100 .
18
04
b1100 $
b1100 /
09
0!
b1100 #
01
16
b1011 *
b1010 '
b1010 -
#225
b1101 $
b1101 /
14
0!
b1101 #
11
b1100 *
b1011 '
b1011 -
#230
0%
0B
0<
1C
08
0A
04
19
b1110 $
b1110 /
1>
b0 .
0=
0!
b1110 #
01
06
1;
b1101 *
b1100 '
b1100 -
#235
b1111 $
b1111 /
14
0!
b1111 #
11
b1110 *
b1101 '
b1101 -
#240
1%
1B
0C
1A
1=
0>
1<
b11100 .
18
04
b0 $
b0 /
09
0!
b0 #
1"
01
16
b1111 *
b1110 '
b1110 -
#245
b1 $
b1 /
14
0!
b1 #
11
b11 )
b0 *
b1111 '
b1111 -
#250
0<
08
0A
0%
19
0>
0=
b11 $
b11 /
0C
b0 .
0B
0!
0"
01
06
0;
0@
b11 #
10
b1 *
b0 '
b0 -
b11 &
b11 ,
#255
1>
1<
18
09
17
b110 .
13
b100 $
b100 /
04
0!
b100 #
11
b10 *
b1 '
b1 -
#260
07
b100 .
03
14
b101 $
b101 /
09
0!
b101 #
01
16
b11 *
b10 '
b10 -
#265
19
17
b110 .
13
b110 $
b110 /
04
0!
b110 #
11
b100 *
b11 '
b11 -
#270
0<
08
07
0C
03
0A
14
19
b111 $
b111 /
1>
b0 .
0=
0!
b111 #
01
06
1;
b101 *
b100 '
b100 -
#275
1C
1A
1=
0>
1<
18
09
17
b1110 .
13
b1000 $
b1000 /
04
0!
b1000 #
11
b110 *
b101 '
b101 -
#280
07
b1100 .
03
14
b1001 $
b1001 /
09
0!
b1001 #
01
16
b111 *
b110 '
b110 -
#285
19
17
b1110 .
13
b1010 $
b1010 /
04
0!
b1010 #
11
b1000 *
b111 '
b111 -
#290
0<
08
07
03
0A
0%
14
19
0>
0=
b1011 $
b1011 /
1C
b0 .
0B
0!
b1011 #
01
06
0;
1@
b1001 *
b1000 '
b1000 -
#295
1>
1<
18
09
17
b110 .
13
b1100 $
b1100 /
04
0!
b1100 #
11
b1010 *
b1001 '
b1001 -
#300
07
b100 .
03
14
b1101 $
b1101 /
09
0!
b1101 #
01
16
b1011 *
b1010 '
b1010 -
#305
19
17
b110 .
13
b1110 $
b1110 /
04
0!
b1110 #
11
b1100 *
b1011 '
b1011 -
#310
0<
08
0%
0B
07
1C
03
0A
14
19
b1111 $
b1111 /
1>
b0 .
0=
0!
b1111 #
01
06
1;
b1101 *
b1100 '
b1100 -
#315
1%
1B
0C
1A
1=
0>
1<
18
09
17
b11110 .
13
b0 $
b0 /
04
0!
b0 #
1"
11
b1110 *
b1101 '
b1101 -
#320
07
b11100 .
03
14
b1 $
b1 /
09
0!
b1 #
01
16
b1111 *
b1110 '
b1110 -
#325
19
17
b11110 .
13
b10 $
b10 /
04
0!
b10 #
11
b100 )
b0 *
b1111 '
b1111 -
#330
0A
0=
09
1>
07
0<
0%
03
08
b100 $
b100 /
0C
b0 .
0B
0!
0"
01
06
0;
0@
b100 #
00
05
1:
b1 *
b0 '
b0 -
b100 &
b100 ,
#335
b101 $
b101 /
14
0!
b101 #
11
b10 *
b1 '
b1 -
#340
04
b110 $
b110 /
19
0!
b110 #
01
16
b11 *
b10 '
b10 -
#345
b111 $
b111 /
14
0!
b111 #
11
b100 *
b11 '
b11 -
#350
1C
1A
b1000 .
1=
04
09
b1000 $
b1000 /
0>
0!
b1000 #
01
06
1;
b101 *
b100 '
b100 -
#355
b1001 $
b1001 /
14
0!
b1001 #
11
b110 *
b101 '
b101 -
#360
04
b1010 $
b1010 /
19
0!
b1010 #
01
16
b111 *
b110 '
b110 -
#365
b1011 $
b1011 /
14
0!
b1011 #
11
b1000 *
b111 '
b111 -
#370
0A
0=
0%
04
09
1>
b1100 $
b1100 /
1C
b0 .
0B
0!
b1100 #
01
06
0;
1@
b1001 *
b1000 '
b1000 -
#375
b1101 $
b1101 /
14
0!
b1101 #
11
b1010 *
b1001 '
b1001 -
#380
04
b1110 $
b1110 /
19
0!
b1110 #
01
16
b1011 *
b1010 '
b1010 -
#385
b1111 $
b1111 /
14
0!
b1111 #
11
b1100 *
b1011 '
b1011 -
#390
1%
1B
0C
1A
b11000 .
1=
04
09
b0 $
b0 /
0>
0!
b0 #
1"
01
06
1;
b1101 *
b1100 '
b1100 -
#395
b1 $
b1 /
14
0!
b1 #
11
b1110 *
b1101 '
b1101 -
#400
04
b10 $
b10 /
19
0!
b10 #
01
16
b1111 *
b1110 '
b1110 -
#405
b11 $
b11 /
14
0!
b11 #
11
b101 )
b0 *
b1111 '
b1111 -
#410
0A
0=
0%
09
1>
b101 $
b101 /
0C
b0 .
0B
0!
0"
01
06
0;
0@
b101 #
10
b1 *
b0 '
b0 -
b101 &
b101 ,
#415
19
17
b10 .
13
b110 $
b110 /
04
0!
b110 #
11
b10 *
b1 '
b1 -
#420
0C
0A
0=
07
1>
03
0<
14
b111 $
b111 /
19
b0 .
08
0!
b111 #
01
16
b11 *
b10 '
b10 -
#425
1C
1A
1=
0>
1<
18
09
17
b1110 .
13
b1000 $
b1000 /
04
0!
b1000 #
11
b100 *
b11 '
b11 -
#430
07
03
0<
14
09
b1000 .
08
b1001 $
b1001 /
0>
0!
b1001 #
01
06
1;
b101 *
b100 '
b100 -
#435
19
17
b1010 .
13
b1010 $
b1010 /
04
0!
b1010 #
11
b110 *
b101 '
b101 -
#440
07
0>
03
0<
14
b1011 $
b1011 /
19
b1000 .
08
0!
b1011 #
01
16
b111 *
b110 '
b110 -
#445
1>
1<
18
09
17
b1110 .
13
b1100 $
b1100 /
04
0!
b1100 #
11
b1000 *
b111 '
b111 -
#450
0A
0=
07
03
0<
0%
14
09
08
1>
b1101 $
b1101 /
1C
b0 .
0B
0!
b1101 #
01
06
0;
1@
b1001 *
b1000 '
b1000 -
#455
19
17
b10 .
13
b1110 $
b1110 /
04
0!
b1110 #
11
b1010 *
b1001 '
b1001 -
#460
0%
0B
1C
0A
0=
07
1>
03
0<
14
b1111 $
b1111 /
19
b0 .
08
0!
b1111 #
01
16
b1011 *
b1010 '
b1010 -
#465
1%
1B
0C
1A
1=
0>
1<
18
09
17
b11110 .
13
b0 $
b0 /
04
0!
b0 #
1"
11
b1100 *
b1011 '
b1011 -
#470
07
03
0<
14
09
b11000 .
08
b1 $
b1 /
0>
0!
b1 #
01
06
1;
b1101 *
b1100 '
b1100 -
#475
19
17
b11010 .
13
b10 $
b10 /
04
0!
b10 #
11
b1110 *
b1101 '
b1101 -
#480
07
0>
03
0<
14
b11 $
b11 /
19
b11000 .
08
0!
b11 #
01
16
b1111 *
b1110 '
b1110 -
#485
1>
1<
18
09
17
b11110 .
13
b100 $
b100 /
04
0!
b100 #
11
b110 )
b0 *
b1111 '
b1111 -
#490
0A
0=
0<
08
19
07
0%
03
1>
b110 $
b110 /
0C
b0 .
0B
0!
0"
01
06
0;
0@
b110 #
00
15
b1 *
b0 '
b0 -
b110 &
b110 ,
#495
b111 $
b111 /
14
0!
b111 #
11
b10 *
b1 '
b1 -
#500
1C
1A
1=
0>
1<
b1100 .
18
04
b1000 $
b1000 /
09
0!
b1000 #
01
16
b11 *
b10 '
b10 -
#505
b1001 $
b1001 /
14
0!
b1001 #
11
b100 *
b11 '
b11 -
#510
0<
b1000 .
08
04
19
b1010 $
b1010 /
0>
0!
b1010 #
01
06
1;
b101 *
b100 '
b100 -
#515
b1011 $
b1011 /
14
0!
b1011 #
11
b110 *
b101 '
b101 -
#520
1>
1<
b1100 .
18
04
b1100 $
b1100 /
09
0!
b1100 #
01
16
b111 *
b110 '
b110 -
#525
b1101 $
b1101 /
14
0!
b1101 #
11
b1000 *
b111 '
b111 -
#530
0A
0=
0<
08
0%
04
19
1>
b1110 $
b1110 /
1C
b0 .
0B
0!
b1110 #
01
06
0;
1@
b1001 *
b1000 '
b1000 -
#535
b1111 $
b1111 /
14
0!
b1111 #
11
b1010 *
b1001 '
b1001 -
#540
1%
1B
0C
1A
1=
0>
1<
b11100 .
18
04
b0 $
b0 /
09
0!
b0 #
1"
01
16
b1011 *
b1010 '
b1010 -
#545
b1 $
b1 /
14
0!
b1 #
11
b1100 *
b1011 '
b1011 -
#550
0<
b11000 .
08
04
19
b10 $
b10 /
0>
0!
b10 #
01
06
1;
b1101 *
b1100 '
b1100 -
#555
b11 $
b11 /
14
0!
b11 #
11
b1110 *
b1101 '
b1101 -
#560
1>
1<
b11100 .
18
04
b100 $
b100 /
09
0!
b100 #
01
16
b1111 *
b1110 '
b1110 -
#565
b101 $
b101 /
14
0!
b101 #
11
b111 )
b0 *
b1111 '
b1111 -
#570
0A
0=
0<
08
0%
19
1>
b111 $
b111 /
0C
b0 .
0B
0!
0"
01
06
0;
0@
b111 #
10
b1 *
b0 '
b0 -
b111 &
b111 ,
#575
1C
1A
1=
0>
1<
18
09
17
b1110 .
13
b1000 $
b1000 /
04
0!
b1000 #
11
b10 *
b1 '
b1 -
#580
07
b1100 .
03
14
b1001 $
b1001 /
09
0!
b1001 #
01
16
b11 *
b10 '
b10 -
#585
19
17
b1110 .
13
b1010 $
b1010 /
04
0!
b1010 #
11
b100 *
b11 '
b11 -
#590
0<
08
07
b1000 .
03
14
19
b1011 $
b1011 /
0>
0!
b1011 #
01
06
1;
b101 *
b100 '
b100 -
#595
1>
1<
18
09
17
b1110 .
13
b1100 $
b1100 /
04
0!
b1100 #
11
b110 *
b101 '
b101 -
#600
07
b1100 .
03
14
b1101 $
b1101 /
09
0!
b1101 #
01
16
b111 *
b110 '
b110 -
#605
19
17
b1110 .
13
b1110 $
b1110 /
04
0!
b1110 #
11
b1000 *
b111 '
b111 -
#610
0A
0=
0<
08
07
03
0%
14
19
1>
b1111 $
b1111 /
1C
b0 .
0B
0!
b1111 #
01
06
0;
1@
b1001 *
b1000 '
b1000 -
#615
1%
1B
0C
1A
1=
0>
1<
18
09
17
b11110 .
13
b0 $
b0 /
04
0!
b0 #
1"
11
b1010 *
b1001 '
b1001 -
#620
07
b11100 .
03
14
b1 $
b1 /
09
0!
b1 #
01
16
b1011 *
b1010 '
b1010 -
#625
19
17
b11110 .
13
b10 $
b10 /
04
0!
b10 #
11
b1100 *
b1011 '
b1011 -
#630
0<
08
07
b11000 .
03
14
19
b11 $
b11 /
0>
0!
b11 #
01
06
1;
b1101 *
b1100 '
b1100 -
#635
1>
1<
18
09
17
b11110 .
13
b100 $
b100 /
04
0!
b100 #
11
b1110 *
b1101 '
b1101 -
#640
07
b11100 .
03
14
b101 $
b101 /
09
0!
b101 #
01
16
b1111 *
b1110 '
b1110 -
#645
19
17
b11110 .
13
b110 $
b110 /
04
0!
b110 #
11
b1000 )
b0 *
b1111 '
b1111 -
#650
0%
0B
09
0>
b1000 $
b1000 /
1C
07
0<
0A
03
08
b0 .
0=
0!
0"
01
06
0;
0@
b1000 #
00
05
0:
1?
b1 *
b0 '
b0 -
b1000 &
b1000 ,
#655
b1001 $
b1001 /
14
0!
b1001 #
11
b10 *
b1 '
b1 -
#660
04
b1010 $
b1010 /
19
0!
b1010 #
01
16
b11 *
b10 '
b10 -
#665
b1011 $
b1011 /
14
0!
b1011 #
11
b100 *
b11 '
b11 -
#670
04
09
b1100 $
b1100 /
1>
0!
b1100 #
01
06
1;
b101 *
b100 '
b100 -
#675
b1101 $
b1101 /
14
0!
b1101 #
11
b110 *
b101 '
b101 -
#680
04
b1110 $
b1110 /
19
0!
b1110 #
01
16
b111 *
b110 '
b110 -
#685
b1111 $
b1111 /
14
0!
b1111 #
11
b1000 *
b111 '
b111 -
#690
1%
b10000 .
1B
04
09
0>
b0 $
b0 /
0C
0!
b0 #
1"
01
06
0;
1@
b1001 *
b1000 '
b1000 -
#695
b1 $
b1 /
14
0!
b1 #
11
b1010 *
b1001 '
b1001 -
#700
04
b10 $
b10 /
19
0!
b10 #
01
16
b1011 *
b1010 '
b1010 -
#705
b11 $
b11 /
14
0!
b11 #
11
b1100 *
b1011 '
b1011 -
#710
04
09
b100 $
b100 /
1>
0!
b100 #
01
06
1;
b1101 *
b1100 '
b1100 -
#715
b101 $
b101 /
14
0!
b101 #
11
b1110 *
b1101 '
b1101 -
#720
04
b110 $
b110 /
19
0!
b110 #
01
16
b1111 *
b1110 '
b1110 -
#725
b111 $
b111 /
14
0!
b111 #
11
b1001 )
b0 *
b1111 '
b1111 -
#730
0%
b0 .
0B
09
0>
b1001 $
b1001 /
1C
0!
0"
01
06
0;
0@
b1001 #
10
b1 *
b0 '
b0 -
b1001 &
b1001 ,
#735
19
17
b10 .
13
b1010 $
b1010 /
04
0!
b1010 #
11
b10 *
b1 '
b1 -
#740
07
0>
03
0<
14
b1011 $
b1011 /
19
b0 .
08
0!
b1011 #
01
16
b11 *
b10 '
b10 -
#745
1>
1<
18
09
17
b110 .
13
b1100 $
b1100 /
04
0!
b1100 #
11
b100 *
b11 '
b11 -
#750
0%
0B
07
1C
03
0<
0A
14
09
08
b1101 $
b1101 /
1>
b0 .
0=
0!
b1101 #
01
06
1;
b101 *
b100 '
b100 -
#755
19
17
b10 .
13
b1110 $
b1110 /
04
0!
b1110 #
11
b110 *
b101 '
b101 -
#760
0%
0B
1C
0A
0=
07
1>
03
0<
14
b1111 $
b1111 /
19
b0 .
08
0!
b1111 #
01
16
b111 *
b110 '
b110 -
#765
1%
1B
0C
1A
1=
0>
1<
18
09
17
b11110 .
13
b0 $
b0 /
04
0!
b0 #
1"
11
b1000 *
b111 '
b111 -
#770
07
03
0<
0A
14
09
08
0>
b10000 .
0=
b1 $
b1 /
0C
0!
b1 #
01
06
0;
1@
b1001 *
b1000 '
b1000 -
#775
19
17
b10010 .
13
b10 $
b10 /
04
0!
b10 #
11
b1010 *
b1001 '
b1001 -
#780
07
0>
03
0<
14
b11 $
b11 /
19
b10000 .
08
0!
b11 #
01
16
b1011 *
b1010 '
b1010 -
#785
1>
1<
18
09
17
b10110 .
13
b100 $
b100 /
04
0!
b100 #
11
b1100 *
b1011 '
b1011 -
#790
07
0C
03
0<
0A
14
09
08
b101 $
b101 /
1>
b10000 .
0=
0!
b101 #
01
06
1;
b1101 *
b1100 '
b1100 -
#795
19
17
b10010 .
13
b110 $
b110 /
04
0!
b110 #
11
b1110 *
b1101 '
b1101 -
#800
0C
0A
0=
07
1>
03
0<
14
b111 $
b111 /
19
b10000 .
08
0!
b111 #
01
16
b1111 *
b1110 '
b1110 -
#805
1C
1A
1=
0>
1<
18
09
17
b11110 .
13
b1000 $
b1000 /
04
0!
b1000 #
11
b1010 )
b0 *
b1111 '
b1111 -
#810
0<
0%
08
0B
19
07
0A
03
0>
b0 .
0=
b1010 $
b1010 /
1C
0!
0"
01
06
0;
0@
b1010 #
00
15
b1 *
b0 '
b0 -
b1010 &
b1010 ,
#815
b1011 $
b1011 /
14
0!
b1011 #
11
b10 *
b1 '
b1 -
#820
1>
1<
b100 .
18
04
b1100 $
b1100 /
09
0!
b1100 #
01
16
b11 *
b10 '
b10 -
#825
b1101 $
b1101 /
14
0!
b1101 #
11
b100 *
b11 '
b11 -
#830
0%
0B
0<
1C
08
0A
04
19
b1110 $
b1110 /
1>
b0 .
0=
0!
b1110 #
01
06
1;
b101 *
b100 '
b100 -
#835
b1111 $
b1111 /
14
0!
b1111 #
11
b110 *
b101 '
b101 -
#840
1%
1B
0C
1A
1=
0>
1<
b11100 .
18
04
b0 $
b0 /
09
0!
b0 #
1"
01
16
b111 *
b110 '
b110 -
#845
b1 $
b1 /
14
0!
b1 #
11
b1000 *
b111 '
b111 -
#850
0<
08
0A
04
19
0>
b10000 .
0=
b10 $
b10 /
0C
0!
b10 #
01
06
0;
1@
b1001 *
b1000 '
b1000 -
#855
b11 $
b11 /
14
0!
b11 #
11
b1010 *
b1001 '
b1001 -
#860
1>
1<
b10100 .
18
04
b100 $
b100 /
09
0!
b100 #
01
16
b1011 *
b1010 '
b1010 -
#865
b101 $
b101 /
14
0!
b101 #
11
b1100 *
b1011 '
b1011 -
#870
0<
0C
08
0A
04
19
b110 $
b110 /
1>
b10000 .
0=
0!
b110 #
01
06
1;
b1101 *
b1100 '
b1100 -
#875
b111 $
b111 /
14
0!
b111 #
11
b1110 *
b1101 '
b1101 -
#880
1C
1A
1=
0>
1<
b11100 .
18
04
b1000 $
b1000 /
09
0!
b1000 #
01
16
b1111 *
b1110 '
b1110 -
#885
b1001 $
b1001 /
14
0!
b1001 #
11
b1011 )
b0 *
b1111 '
b1111 -
#890
0%
0B
0<
08
0A
19
0>
b0 .
0=
b1011 $
b1011 /
1C
0!
0"
01
06
0;
0@
b1011 #
10
b1 *
b0 '
b0 -
b1011 &
b1011 ,
#895
1>
1<
18
09
17
b110 .
13
b1100 $
b1100 /
04
0!
b1100 #
11
b10 *
b1 '
b1 -
#900
07
b100 .
03
14
b1101 $
b1101 /
09
0!
b1101 #
01
16
b11 *
b10 '
b10 -
#905
19
17
b110 .
13
b1110 $
b1110 /
04
0!
b1110 #
11
b100 *
b11 '
b11 -
#910
0<
08
0%
0B
07
1C
03
0A
14
19
b1111 $
b1111 /
1>
b0 .
0=
0!
b1111 #
01
06
1;
b101 *
b100 '
b100 -
#915
1%
1B
0C
1A
1=
0>
1<
18
09
17
b11110 .
13
b0 $
b0 /
04
0!
b0 #
1"
11
b110 *
b101 '
b101 -
#920
07
b11100 .
03
14
b1 $
b1 /
09
0!
b1 #
01
16
b111 *
b110 '
b110 -
#925
19
17
b11110 .
13
b10 $
b10 /
04
0!
b10 #
11
b1000 *
b111 '
b111 -
#930
0<
08
07
03
0A
14
19
0>
b10000 .
0=
b11 $
b11 /
0C
0!
b11 #
01
06
0;
1@
b1001 *
b1000 '
b1000 -
#935
1>
1<
18
09
17
b10110 .
13
b100 $
b100 /
04
0!
b100 #
11
b1010 *
b1001 '
b1001 -
#940
07
b10100 .
03
14
b101 $
b101 /
09
0!
b101 #
01
16
b1011 *
b1010 '
b1010 -
#945
19
17
b10110 .
13
b110 $
b110 /
04
0!
b110 #
11
b1100 *
b1011 '
b1011 -
#950
0<
08
07
0C
03
0A
14
19
b111 $
b111 /
1>
b10000 .
0=
0!
b111 #
01
06
1;
b1101 *
b1100 '
b1100 -
#955
1C
1A
1=
0>
1<
18
09
17
b11110 .
13
b1000 $
b1000 /
04
0!
b1000 #
11
b1110 *
b1101 '
b1101 -
#960
07
b11100 .
03
14
b1001 $
b1001 /
09
0!
b1001 #
01
16
b1111 *
b1110 '
b1110 -
#965
19
17
b11110 .
13
b1010 $
b1010 /
04
0!
b1010 #
11
b1100 )
b0 *
b1111 '
b1111 -
#970
0%
0B
0A
0=
09
1>
07
0<
03
b0 .
08
b1100 $
b1100 /
1C
0!
0"
01
06
0;
0@
b1100 #
00
05
1:
b1 *
b0 '
b0 -
b1100 &
b1100 ,
#975
b1101 $
b1101 /
14
0!
b1101 #
11
b10 *
b1 '
b1 -
#980
04
b1110 $
b1110 /
19
0!
b1110 #
01
16
b11 *
b10 '
b10 -
#985
b1111 $
b1111 /
14
0!
b1111 #
11
b100 *
b11 '
b11 -
#990
1%
1B
0C
1A
b11000 .
1=
04
09
b0 $
b0 /
0>
0!
b0 #
1"
01
06
1;
b101 *
b100 '
b100 -
#995
b1 $
b1 /
14
0!
b1 #
11
b110 *
b101 '
b101 -
#1000
04
b10 $
b10 /
19
0!
b10 #
01
16
b111 *
b110 '
b110 -
